Claro/__init__.py
Claro/models.py
Claro/test.py
Pyclaro-0.1.dist-info/LICENSE.txt
Pyclaro-0.1.dist-info/METADATA
Pyclaro-0.1.dist-info/WHEEL
Pyclaro-0.1.dist-info/top_level.txt
Pyclaro-0.1.dist-info/RECORD
