Metadata-Version: 2.1
Name: Pyclaro
Version: 0.1
Summary: This is a CLI based Application
Author: HNG Team Claro
Author-email: vamc44@gmail.com
Classifier: Programming Language :: Python :: 3
Classifier: License :: OSI Approved :: MIT License
Classifier: Operating System :: OS Independent
License-File: LICENSE.txt
